speechcluster/__init__.py
speechcluster/__main__.py
speechcluster/sc.py
speechcluster/segDiBo.py
speechcluster/segFake.py
speechcluster/segInter.py
speechcluster/segMerge.py
speechcluster/segReplace.py
speechcluster/segSwitch.py
speechcluster/speechCluster.py
speechcluster/splitAll.py
speechcluster/trim.py
speechcluster/utils.py
speechcluster-3.0.5.dist-info/LICENSE
speechcluster-3.0.5.dist-info/METADATA
speechcluster-3.0.5.dist-info/WHEEL
speechcluster-3.0.5.dist-info/entry_points.txt
speechcluster-3.0.5.dist-info/top_level.txt
speechcluster-3.0.5.dist-info/RECORD
