Metadata-Version: 2.2
Name: speechcluster
Version: 3.0.5
Summary: A speech database builder's multitool
Author-email: Ivan Uemlianin <ivan@llaisdy.co.uk>
Project-URL: Homepage, https://github.com/llaisdy/speechcluster
Project-URL: Issues, https://github.com/llaisdy/speechcluster/issues
Classifier: Programming Language :: Python :: 3
Classifier: License :: OSI Approved :: MIT License
Classifier: Operating System :: OS Independent
Requires-Python: >=3.12
License-File: LICENSE
